PythonShujuKexueBenzhilunChuyiFix1/README.md
PythonShujuKexueBenzhilunChuyiFix1/__init__.py
PythonShujuKexueBenzhilunChuyiFix1/__main__.py
PythonShujuKexueBenzhilunChuyiFix1/file.epub
PythonShujuKexueBenzhilunChuyiFix1/index.html
PythonShujuKexueBenzhilunChuyiFix1/css/__init__.py
PythonShujuKexueBenzhilunChuyiFix1/css/annotations.css
PythonShujuKexueBenzhilunChuyiFix1/css/main.css
PythonShujuKexueBenzhilunChuyiFix1/css/normalize.css
PythonShujuKexueBenzhilunChuyiFix1/css/popup.css
PythonShujuKexueBenzhilunChuyiFix1/font/__init__.py
PythonShujuKexueBenzhilunChuyiFix1/font/fontello.eot
PythonShujuKexueBenzhilunChuyiFix1/font/fontello.svg
PythonShujuKexueBenzhilunChuyiFix1/font/fontello.ttf
PythonShujuKexueBenzhilunChuyiFix1/font/fontello.woff
PythonShujuKexueBenzhilunChuyiFix1/img/__init__.py
PythonShujuKexueBenzhilunChuyiFix1/img/annotator-glyph-sprite.png
PythonShujuKexueBenzhilunChuyiFix1/img/annotator-icon-sprite.png
PythonShujuKexueBenzhilunChuyiFix1/img/apple-touch-icon.png
PythonShujuKexueBenzhilunChuyiFix1/img/cancelfullscreen.png
PythonShujuKexueBenzhilunChuyiFix1/img/close.png
PythonShujuKexueBenzhilunChuyiFix1/img/fullscreen.png
PythonShujuKexueBenzhilunChuyiFix1/img/loader.gif
PythonShujuKexueBenzhilunChuyiFix1/img/menu-icon.png
PythonShujuKexueBenzhilunChuyiFix1/img/save.png
PythonShujuKexueBenzhilunChuyiFix1/img/saved.png
PythonShujuKexueBenzhilunChuyiFix1/img/settings-s.png
PythonShujuKexueBenzhilunChuyiFix1/img/settings.png
PythonShujuKexueBenzhilunChuyiFix1/img/star.png
PythonShujuKexueBenzhilunChuyiFix1/js/__init__.py
PythonShujuKexueBenzhilunChuyiFix1/js/epub.js
PythonShujuKexueBenzhilunChuyiFix1/js/epub.min.js
PythonShujuKexueBenzhilunChuyiFix1/js/epub.min.map
PythonShujuKexueBenzhilunChuyiFix1/js/hooks.min.js
PythonShujuKexueBenzhilunChuyiFix1/js/hooks.min.map
PythonShujuKexueBenzhilunChuyiFix1/js/reader.js
PythonShujuKexueBenzhilunChuyiFix1/js/reader.js.map
PythonShujuKexueBenzhilunChuyiFix1/js/reader.min.js
python_shuju_kexue_benzhilun_chuyi_fix1-2025.3.25.1.dist-info/METADATA
python_shuju_kexue_benzhilun_chuyi_fix1-2025.3.25.1.dist-info/WHEEL
python_shuju_kexue_benzhilun_chuyi_fix1-2025.3.25.1.dist-info/entry_points.txt
python_shuju_kexue_benzhilun_chuyi_fix1-2025.3.25.1.dist-info/top_level.txt
python_shuju_kexue_benzhilun_chuyi_fix1-2025.3.25.1.dist-info/RECORD
